LICENSE
MANIFEST.in
README.md
pyproject.toml
setup.py
tap_circle_ci/__init__.py
tap_circle_ci/client.py
tap_circle_ci/discover.py
tap_circle_ci/exceptions.py
tap_circle_ci/sync.py
tap_circle_ci.egg-info/PKG-INFO
tap_circle_ci.egg-info/SOURCES.txt
tap_circle_ci.egg-info/dependency_links.txt
tap_circle_ci.egg-info/entry_points.txt
tap_circle_ci.egg-info/requires.txt
tap_circle_ci.egg-info/top_level.txt
tap_circle_ci/schemas/jobs.json
tap_circle_ci/schemas/pipelines.json
tap_circle_ci/schemas/workflows.json
tap_circle_ci/streams/__init__.py
tap_circle_ci/streams/abstracts.py
tap_circle_ci/streams/jobs.py
tap_circle_ci/streams/pipelines.py
tap_circle_ci/streams/workflows.py