Metadata-Version: 2.1
Name: tap-circle-ci
Version: 1.0.0
Summary: Singer.io tap for extracting data from circle ci
Home-page: https://singer.io
Author: Sisu Data;Stitch
License: UNKNOWN
Platform: UNKNOWN
Classifier: Programming Language :: Python :: 3 :: Only
Provides-Extra: dev
